showast2/__init__.py
showast2/asts.py
showast2/rendering/__init__.py
showast2/rendering/graphviz.py
showast2/rendering/nltk.py
showast2/util/__init__.py
showast2/util/contextmanagers.py
showast2-0.3.2.dist-info/LICENSE.txt
showast2-0.3.2.dist-info/METADATA
showast2-0.3.2.dist-info/WHEEL
showast2-0.3.2.dist-info/top_level.txt
showast2-0.3.2.dist-info/RECORD
