Metadata-Version: 2.2
Name: showast2
Version: 0.3.2
Summary: IPython notebook plugin for visualizing abstract syntax trees. Unofficial update for Python >= 3.12 by Andreas Zeller.
Home-page: https://github.com/hchasestevens/show_ast
Author: H. Chase Stevens
Author-email: chase@chasestevens.com
License: MIT
Keywords: ipython jupyter notebook ast asts graphing visualization syntax
Classifier: Development Status :: 3 - Alpha
Classifier: Programming Language :: Python
Classifier: Programming Language :: Python :: 2
Classifier: Programming Language :: Python :: 2.7
Classifier: Intended Audience :: Developers
Classifier: Operating System :: OS Independent
Classifier: License :: OSI Approved :: MIT License
Classifier: Natural Language :: English
Classifier: Topic :: Software Development :: Code Generators
Classifier: Framework :: IPython
Classifier: Topic :: Multimedia :: Graphics :: Presentation
License-File: LICENSE.txt
Requires-Dist: ipython
Requires-Dist: graphviz
Provides-Extra: nltk
Requires-Dist: nltk; extra == "nltk"
Requires-Dist: pillow; extra == "nltk"
Dynamic: author
Dynamic: author-email
Dynamic: classifier
Dynamic: home-page
Dynamic: keywords
Dynamic: license
Dynamic: provides-extra
Dynamic: requires-dist
Dynamic: summary
